activatable_model/__init__.py
activatable_model/apps.py
activatable_model/models.py
activatable_model/signals.py
activatable_model/urls.py
activatable_model/validation.py
activatable_model/version.py
activatable_model/tests/__init__.py
activatable_model/tests/models.py
activatable_model/tests/tests.py
activatable_model/tests/migrations/0001_initial.py
activatable_model/tests/migrations/0002_activatablemodelwrelandcascade.py
activatable_model/tests/migrations/__init__.py
django_activatable_model-3.1.0.dist-info/LICENSE
django_activatable_model-3.1.0.dist-info/METADATA
django_activatable_model-3.1.0.dist-info/WHEEL
django_activatable_model-3.1.0.dist-info/top_level.txt
django_activatable_model-3.1.0.dist-info/RECORD
